svgtools
