Metadata-Version: 1.0
Name: svgtools
Version: 0.0.2
Summary: components from images and data for interactive visualizations
Home-page: http://www.github.com/vsoch/svgtools
Author: Vanessa Sochat
Author-email: vsochat@stanford.edu
License: LICENSE.txt
Platform: UNKNOWN
